{"type": "Feature", "id": 56051957, "geometry": {"type": "Point", "coordinates": [12.72855, 48.394588]}, "properties": {"woe:id": 56051957, "woe:parent_id": 646660, "woe:name": "Flugplatz Eggenfelden", "woe:placetype": 14, "woe:placetype_name": "Airport", "woe:lang": "GER", "iso:country": "DE", "meta:provider": ["geoplanet:7.3.1", "geoplanet:7.3.2", "geoplanet:7.4.0", "geoplanet:7.4.1", "geoplanet:7.5.1", "geoplanet:7.5.2", "geoplanet:7.6.0", "geoplanet:7.8.1", "geoplanet:7.9.0", "geoplanet:7.10.0", "geoplanet:8.0.0", "woeplanet:8.0.0"], "meta:indexed": "2020-08-20T20:50:56.661018", "meta:updated": "2020-10-14T11:05:29.316374", "woe:hierarchy": {"continent": 24865675, "country": 23424829, "town": 0, "planet": 1, "county": 12596743, "suburb": 0, "state": 2345482, "region": 0, "localadmin": 12623000}, "woe:timezone_id": 28350890, "woe:hash": "u29539uwutnf", "woe:centroid": [12.72855, 48.394588], "geom:latitude": 48.394588, "geom:longitude": 12.72855, "geom:hash": "u29539uwutnf", "woe:latitude": 48.394588, "geom:centroid": [12.72855, 48.394588], "woe:longitude": 12.72855, "woe:repo": "woeplanet-airport-de", "geom:area": 0.0, "woe:scale": 19}}