{"type": "Feature", "id": 56052215, "geometry": {"type": "Point", "coordinates": [8.20884, 48.87117]}, "properties": {"woe:id": 56052215, "woe:parent_id": 686965, "woe:name": "Segelfluggel\u00e4nde Rastatt", "woe:placetype": 14, "woe:placetype_name": "Airport", "woe:lang": "GER", "iso:country": "DE", "meta:provider": ["geoplanet:7.3.1", "geoplanet:7.3.2", "geoplanet:7.4.0", "geoplanet:7.4.1", "geoplanet:7.5.1", "geoplanet:7.5.2", "geoplanet:7.6.0", "geoplanet:7.8.1", "geoplanet:7.9.0", "geoplanet:7.10.0", "geoplanet:8.0.0", "woeplanet:8.0.0"], "meta:indexed": "2020-08-20T20:50:56.887715", "meta:updated": "2020-10-14T11:05:29.221502", "woe:alias_GER_S": ["Segelfluggelande Rastatt"], "woe:hierarchy": {"continent": 24865675, "country": 23424829, "town": 0, "planet": 1, "county": 12596863, "suburb": 0, "state": 2345481, "region": 0, "localadmin": 12623917}, "woe:timezone_id": 28350890, "woe:hash": "u0ty4b9rpy6s", "woe:centroid": [8.20884, 48.87117], "geom:latitude": 48.87117, "geom:longitude": 8.20884, "geom:hash": "u0ty4b9rpy6s", "woe:latitude": 48.87117, "geom:centroid": [8.20884, 48.87117], "woe:longitude": 8.20884, "woe:repo": "woeplanet-airport-de", "geom:area": 0.0, "woe:scale": 19}}