{"type": "Feature", "id": 56051973, "properties": {"woe:id": 56051973, "woe:parent_id": 663248, "woe:name": "Flugplatz Lauf-lillinghof", "woe:placetype": 14, "woe:placetype_name": "Airport", "woe:lang": "GER", "iso:country": "DE", "meta:provider": ["geoplanet:7.3.1", "geoplanet:7.3.2", "geoplanet:7.4.0", "geoplanet:7.4.1", "geoplanet:7.5.1", "geoplanet:7.5.2", "geoplanet:7.6.0", "geoplanet:7.8.1", "geoplanet:7.9.0", "geoplanet:7.10.0", "geoplanet:8.0.0", "woeplanet:8.0.0"], "meta:indexed": "2020-08-20T20:50:56.675676", "meta:updated": "2020-08-22T01:51:21.846677", "woe:alias_GER_V": ["Segelflugplatz Lauf-Lillinghof"], "woe:hierarchy": {"continent": 24865675, "country": 23424829, "town": 0, "planet": 1, "county": 12596857, "suburb": 0, "state": 2345482, "region": 0, "localadmin": 12634367}, "woe:timezone_id": 28350890, "woe:hash": "u2b40y75mg7m", "woe:centroid": [11.28733, 49.605221], "geom:latitude": 49.605221, "geom:longitude": 11.28733, "geom:hash": "u2b40y75mg7m", "woe:latitude": 49.605221, "geom:centroid": [11.28733, 49.605221], "woe:longitude": 11.28733, "woe:repo": "woeplanet-airport-de"}, "geometry": {"coordinates": [11.28733, 49.605221], "type": "Point"}}