{"type": "Feature", "id": 22235857, "properties": {"woe:id": 22235857, "woe:parent_id": 29350602, "woe:name": "Langeoog Airport", "woe:placetype": 14, "woe:placetype_name": "Airport", "woe:lang": "ENG", "iso:country": "DE", "meta:provider": ["geoplanet:7.3.1", "geoplanet:7.3.2", "geoplanet:7.4.0", "geoplanet:7.4.1", "geoplanet:7.5.1", "geoplanet:7.5.2", "geoplanet:7.6.0", "geoplanet:7.8.1", "geoplanet:7.9.0", "geoplanet:7.10.0", "geoplanet:8.0.0", "woeplanet:8.0.0"], "meta:indexed": "2020-08-20T20:50:56.559430", "woe:alias_ENG_V": ["LGO", "LGO Airport"], "woe:alias_GER_Q": ["Flughafen Langeoog"], "meta:updated": "2020-08-22T01:51:21.782402", "woe:alias_GER_V": ["LGO Flughafen"], "woe:hierarchy": {"continent": 24865675, "country": 23424829, "town": 0, "planet": 1, "county": 12596728, "suburb": 0, "state": 2345486, "region": 0, "localadmin": 12629809}, "woe:timezone_id": 28350890, "woe:hash": "u1t3dr97zw9s", "woe:centroid": [7.48373, 53.74305], "geom:latitude": 53.74305, "geom:longitude": 7.48373, "geom:hash": "u1t3dr97zw9s", "woe:latitude": 53.74305, "geom:centroid": [7.48373, 53.74305], "woe:longitude": 7.48373, "woe:repo": "woeplanet-airport-de"}, "geometry": {"coordinates": [7.48373, 53.74305], "type": "Point"}}