{"type": "Feature", "id": 22206577, "geometry": {"type": "Point", "coordinates": [7.69564, 52.13076]}, "properties": {"woe:id": 22206577, "woe:parent_id": 692395, "woe:name": "Munster-Osnabruck International Airport", "woe:placetype": 14, "woe:placetype_name": "Airport", "woe:lang": "ENG", "iso:country": "DE", "meta:provider": ["geoplanet:7.3.1", "geoplanet:7.3.2", "geoplanet:7.4.0", "geoplanet:7.4.1", "geoplanet:7.5.1", "geoplanet:7.5.2", "geoplanet:7.6.0", "geoplanet:7.8.1", "geoplanet:7.9.0", "geoplanet:7.10.0", "geoplanet:8.0.0", "woeplanet:8.0.0"], "meta:indexed": "2020-08-20T20:50:56.609765", "woe:alias_FIN_V": ["Munsterin Lentokentta", "Munsterin Lentokentt\u00e4"], "woe:alias_ENG_V": ["M\u00fcnster-Osnabr\u00fcck Airport", "Munster-Osnabruck Airport", "FMO Airport", "Munster-Osnabruck", "FMO"], "woe:alias_ITA_V": ["Aeroporto Di M\u00fcnster-Osnabr\u00fcck", "Aeroporto Di Munster-Osnabruck"], "woe:alias_DAN_V": ["Munster-Osnabruck Lufthavn", "M\u00fcnster-Osnabr\u00fcck Lufthavn"], "woe:alias_DUT_V": ["Luchthaven Munster-Osnabruck", "Luchthaven M\u00fcnster-Osnabr\u00fcck"], "woe:alias_POR_V": ["Aeroporto de Munster-Osnabruck", "Aeroporto de M\u00fcnster-Osnabr\u00fcck"], "woe:alias_SWE_V": ["M\u00fcnster-Osnabr\u00fcck Flygplats", "Munster-Osnabruck Flygplats"], "woe:alias_GER_Q": ["Flughafen M\u00fcnster Osnabr\u00fcck"], "meta:updated": "2020-10-14T11:05:29.398006", "woe:alias_GER_V": ["Flughafen Munster-Osnabruck", "Flughafen M\u00fcnster-Osnabr\u00fcck", "FMO Flughafen"], "woe:alias_FRE_V": ["Aeroport de Munster-Osnabruck", "A\u00e9roport de M\u00fcnster-Osnabr\u00fcck"], "woe:alias_GER_S": ["Flughafen Munster Osnabruck", "Flughafen Muenster Osnabrueck"], "woe:alias_SPA_V": ["Aeropuerto de Munster-Osnabruck", "Aeropuerto de M\u00fcnster-Osnabr\u00fcck"], "woe:alias_FIN_S": ["Munsterin Lentokentta"], "woe:alias_FRE_Q": ["A\u00e9roport de M\u00fcnster-Osnabr\u00fcck"], "woe:alias_FIN_Q": ["Munsterin Lentokentt\u00e4"], "woe:alias_DUT_S": ["Luchthaven Munster-Osnabruck"], "woe:alias_HUN_V": ["M\u00fcnster-Osnabr\u00fcck Rep\u00fcl\u0151t\u00e9r", "Munster-Osnabruck Repuloter"], "woe:alias_DUT_Q": ["Luchthaven M\u00fcnster-Osnabr\u00fcck"], "woe:alias_SPA_Q": ["Aeropuerto de M\u00fcnster-Osnabr\u00fcck"], "woe:alias_FRE_S": ["Aeroport de Munster-Osnabruck"], "woe:alias_SPA_S": ["Aeropuerto de Munster-Osnabruck"], "woe:alias_POR_S": ["Aeroporto de Munster-Osnabruck"], "woe:alias_POL_V": ["Port Lotniczy Munster-Osnabruck"], "woe:alias_POR_Q": ["Aeroporto de M\u00fcnster-Osnabr\u00fcck"], "woe:alias_DAN_Q": ["M\u00fcnster-Osnabr\u00fcck Lufthavn"], "woe:alias_CZE_V": ["Leti\u0161t\u011b M\u00fcnster-Osnabr\u00fcck", "Letiste Munster-Osnabruck"], "woe:alias_DAN_S": ["Munster-Osnabruck Lufthavn"], "woe:alias_UNK_V": ["Letisko Munster-Osnabruc", "Letisko M\u00fcnster-Osnabr\u00fcc", "\u0391\u03b5\u03c1\u03bf\u03b4\u03c1\u03bfmu\u03b9\u03bf \u039c\u03b9\u03bd\u03c3\u03c4\u03b5\u03c1-\u039f\u03c3\u03bd\u03b1mu\u03c0\u03c1\u03bf\u03c5\u03ba", "\u0391\u03b5\u03c1\u03bf\u03b4\u03c1\u03bf\u03bc\u03b9\u03bf \u039c\u03b9\u03bd\u03c3\u03c4\u03b5\u03c1-\u039f\u03c3\u03bd\u03b1\u03bc\u03c0\u03c1\u03bf\u03c5\u03ba", "\u0410\u044d\u0440\u043e\u043f\u043e\u0440\u0442 \u041c\u044e\u043d\u0441\u0442\u0435\u0440-\u041e\u0441\u043d\u0430\u0431\u0440\u044e\u043a", "Letisko M\u00fcnster-Osnabr\u00fcck", "Letisko Munster-Osnabruck"], "woe:alias_SWE_Q": ["M\u00fcnster-Osnabr\u00fcck Flygplats"], "woe:alias_ITA_Q": ["Aeroporto Di M\u00fcnster-Osnabr\u00fcck"], "woe:alias_ITA_S": ["Aeroporto Di Munster-Osnabruck"], "woe:alias_SWE_S": ["Munster-Osnabruck Flygplats"], "woe:hierarchy": {"continent": 24865675, "country": 23424829, "town": 0, "planet": 1, "county": 12596690, "suburb": 0, "state": 2345487, "region": 0, "localadmin": 12624303}, "woe:timezone_id": 28350890, "woe:hash": "u1m2x45g9qj0", "woe:centroid": [7.69564, 52.13076], "geom:latitude": 52.13076, "geom:longitude": 7.69564, "geom:hash": "u1m2x45g9qj0", "woe:latitude": 52.13076, "geom:centroid": [7.69564, 52.13076], "woe:longitude": 7.69564, "woe:repo": "woeplanet-airport-de", "geom:area": 0.0, "woe:scale": 19}}