{"type": "Feature", "id": 12513224, "geometry": {"type": "Point", "coordinates": [13.8234, 51.4361]}, "properties": {"woe:id": 12513224, "woe:parent_id": 690331, "woe:name": "Ruhland Highway Strip Airport", "woe:placetype": 14, "woe:placetype_name": "Airport", "woe:lang": "ENG", "iso:country": "DE", "meta:provider": ["geoplanet:7.3.1", "geoplanet:7.3.2", "geoplanet:7.4.0", "geoplanet:7.4.1", "geoplanet:7.5.1", "geoplanet:7.5.2", "geoplanet:7.6.0", "geoplanet:7.8.1", "geoplanet:7.9.0", "geoplanet:7.10.0", "geoplanet:8.0.0", "woeplanet:8.0.0"], "meta:indexed": "2020-08-20T20:50:56.513135", "woe:alias_GER_Q": ["Flughafen Ruhland Highway Strip"], "meta:updated": "2020-10-14T11:05:29.413837", "woe:hierarchy": {"continent": 24865675, "country": 23424829, "town": 0, "planet": 1, "county": 12596972, "suburb": 0, "state": 2345491, "region": 0, "localadmin": 12633416}, "woe:timezone_id": 28350890, "woe:hash": "u31ude9uuxfp", "woe:centroid": [13.8234, 51.4361], "geom:latitude": 51.4361, "geom:longitude": 13.8234, "geom:hash": "u31ude9uuxfp", "woe:latitude": 51.4361, "geom:centroid": [13.8234, 51.4361], "woe:longitude": 13.8234, "woe:repo": "woeplanet-airport-de", "geom:area": 0.0, "woe:scale": 19}}