{"type": "Feature", "id": 56051951, "geometry": {"type": "Point", "coordinates": [11.46399, 50.133621]}, "properties": {"woe:id": 56051951, "woe:parent_id": 669470, "woe:name": "Flugplatz Kulmbach", "woe:placetype": 14, "woe:placetype_name": "Airport", "woe:lang": "GER", "iso:country": "DE", "meta:provider": ["geoplanet:7.3.1", "geoplanet:7.3.2", "geoplanet:7.4.0", "geoplanet:7.4.1", "geoplanet:7.5.1", "geoplanet:7.5.2", "geoplanet:7.6.0", "geoplanet:7.8.1", "geoplanet:7.9.0", "geoplanet:7.10.0", "geoplanet:8.0.0", "woeplanet:8.0.0"], "meta:indexed": "2020-08-20T20:50:56.656104", "meta:updated": "2020-10-14T11:05:29.309091", "woe:hierarchy": {"continent": 24865675, "country": 23424829, "town": 0, "planet": 1, "county": 12596862, "suburb": 0, "state": 2345482, "region": 0, "localadmin": 12635350}, "woe:timezone_id": 28350890, "woe:hash": "u2bjhyecd26d", "woe:centroid": [11.46399, 50.133621], "geom:latitude": 50.133621, "geom:longitude": 11.46399, "geom:hash": "u2bjhyecd26d", "woe:latitude": 50.133621, "geom:centroid": [11.46399, 50.133621], "woe:longitude": 11.46399, "woe:repo": "woeplanet-airport-de", "geom:area": 0.0, "woe:scale": 19}}