{"type": "Feature", "id": 56052112, "geometry": {"type": "Point", "coordinates": [10.11641, 52.68713]}, "properties": {"woe:id": 56052112, "woe:parent_id": 643099, "woe:name": "Flugplatz Arloh", "woe:placetype": 14, "woe:placetype_name": "Airport", "woe:lang": "GER", "iso:country": "DE", "meta:provider": ["geoplanet:7.3.1", "geoplanet:7.3.2", "geoplanet:7.4.0", "geoplanet:7.4.1", "geoplanet:7.5.1", "geoplanet:7.5.2", "geoplanet:7.6.0", "geoplanet:7.8.1", "geoplanet:7.9.0", "geoplanet:7.10.0", "geoplanet:8.0.0", "woeplanet:8.0.0"], "meta:indexed": "2020-08-20T20:50:56.796647", "meta:updated": "2020-10-14T11:05:29.370093", "woe:hierarchy": {"continent": 24865675, "country": 23424829, "town": 0, "planet": 1, "county": 12596807, "suburb": 0, "state": 2345486, "region": 0, "localadmin": 12629600}, "woe:timezone_id": 28350890, "woe:hash": "u1r5wpqsc2yh", "woe:centroid": [10.11641, 52.68713], "geom:latitude": 52.68713, "geom:longitude": 10.11641, "geom:hash": "u1r5wpqsc2yh", "woe:latitude": 52.68713, "geom:centroid": [10.11641, 52.68713], "woe:longitude": 10.11641, "woe:repo": "woeplanet-airport-de", "geom:area": 0.0, "woe:scale": 19}}