{"type": "Feature", "id": 56052119, "geometry": {"type": "Point", "coordinates": [10.22112, 53.967892]}, "properties": {"woe:id": 56052119, "woe:parent_id": 703239, "woe:name": "Flugplatz Wahlstedt", "woe:placetype": 14, "woe:placetype_name": "Airport", "woe:lang": "GER", "iso:country": "DE", "meta:provider": ["geoplanet:7.3.1", "geoplanet:7.3.2", "geoplanet:7.4.0", "geoplanet:7.4.1", "geoplanet:7.5.1", "geoplanet:7.5.2", "geoplanet:7.6.0", "geoplanet:7.8.1", "geoplanet:7.9.0", "geoplanet:7.10.0", "geoplanet:8.0.0", "woeplanet:8.0.0"], "meta:indexed": "2020-08-20T20:50:56.802353", "meta:updated": "2020-10-14T11:05:29.337230", "woe:hierarchy": {"continent": 24865675, "country": 23424829, "town": 0, "planet": 1, "county": 12597010, "suburb": 0, "state": 2345490, "region": 0, "localadmin": 12631739}, "woe:timezone_id": 28350890, "woe:hash": "u1x708dcc25r", "woe:centroid": [10.22112, 53.967892], "geom:latitude": 53.967892, "geom:longitude": 10.22112, "geom:hash": "u1x708dcc25r", "woe:latitude": 53.967892, "geom:centroid": [10.22112, 53.967892], "woe:longitude": 10.22112, "woe:repo": "woeplanet-airport-de", "geom:area": 0.0, "woe:scale": 19}}