{"type": "Feature", "id": 56052206, "geometry": {"type": "Point", "coordinates": [9.28852, 48.457539]}, "properties": {"woe:id": 56052206, "woe:parent_id": 15002691, "woe:name": "Segelfluggel\u00e4nde \u00dcbersberg", "woe:placetype": 14, "woe:placetype_name": "Airport", "woe:lang": "GER", "iso:country": "DE", "meta:provider": ["geoplanet:7.3.1", "geoplanet:7.3.2", "geoplanet:7.4.0", "geoplanet:7.4.1", "geoplanet:7.5.1", "geoplanet:7.5.2", "geoplanet:7.6.0", "geoplanet:7.8.1", "geoplanet:7.9.0", "geoplanet:7.10.0", "geoplanet:8.0.0", "woeplanet:8.0.0"], "meta:indexed": "2020-08-20T20:50:56.879363", "meta:updated": "2020-10-14T11:05:29.232961", "woe:alias_GER_S": ["Segelfluggelande Ubersberg"], "woe:hierarchy": {"continent": 24865675, "country": 23424829, "town": 0, "planet": 1, "county": 12596909, "suburb": 0, "state": 2345481, "region": 0, "localadmin": 12623637}, "woe:timezone_id": 28350890, "woe:hash": "u0weem7tw5yx", "woe:centroid": [9.28852, 48.457539], "geom:latitude": 48.457539, "geom:longitude": 9.28852, "geom:hash": "u0weem7tw5yx", "woe:latitude": 48.457539, "geom:centroid": [9.28852, 48.457539], "woe:longitude": 9.28852, "woe:repo": "woeplanet-airport-de", "geom:area": 0.0, "woe:scale": 19}}