{"type": "Feature", "id": 56052150, "properties": {"woe:id": 56052150, "woe:parent_id": 677493, "woe:name": "Segelfluggel\u00e4nde Neresheim", "woe:placetype": 14, "woe:placetype_name": "Airport", "woe:lang": "GER", "iso:country": "DE", "meta:provider": ["geoplanet:7.3.1", "geoplanet:7.3.2", "geoplanet:7.4.0", "geoplanet:7.4.1", "geoplanet:7.5.1", "geoplanet:7.5.2", "geoplanet:7.6.0", "geoplanet:7.8.1", "geoplanet:7.9.0", "geoplanet:7.10.0", "geoplanet:8.0.0", "woeplanet:8.0.0"], "meta:indexed": "2020-08-20T20:50:56.830837", "meta:updated": "2020-08-22T01:51:21.909992", "woe:alias_GER_S": ["Segelfluggelande Neresheim"], "woe:hierarchy": {"continent": 24865675, "country": 23424829, "town": 0, "planet": 1, "county": 12596698, "suburb": 0, "state": 2345481, "region": 0, "localadmin": 12624225}, "woe:timezone_id": 28350890, "woe:hash": "u0xm71022bss", "woe:centroid": [10.32753, 48.740891], "geom:latitude": 48.740891, "geom:longitude": 10.32753, "geom:hash": "u0xm71022bss", "woe:latitude": 48.740891, "geom:centroid": [10.32753, 48.740891], "woe:longitude": 10.32753, "woe:repo": "woeplanet-airport-de"}, "geometry": {"coordinates": [10.32753, 48.740891], "type": "Point"}}