{"type": "Feature", "id": 22656464, "geometry": {"type": "Point", "coordinates": [9.38236, 51.807381]}, "properties": {"woe:id": 22656464, "woe:parent_id": 633756, "woe:name": "Hoxter-Holzminden Airport", "woe:placetype": 14, "woe:placetype_name": "Airport", "woe:lang": "ENG", "iso:country": "DE", "meta:provider": ["geoplanet:7.3.1", "geoplanet:7.3.2", "geoplanet:7.4.0", "geoplanet:7.4.1", "geoplanet:7.5.1", "geoplanet:7.5.2", "geoplanet:7.6.0", "geoplanet:7.8.1", "geoplanet:7.9.0", "geoplanet:7.10.0", "geoplanet:8.0.0", "woeplanet:8.0.0"], "meta:indexed": "2020-08-20T20:50:56.628331", "woe:alias_GER_Q": ["H\u00f6xter Holzminden"], "meta:updated": "2020-10-14T11:05:29.199031", "woe:alias_GER_V": ["Flughafen H\u00f6xter Holzminden"], "woe:alias_GER_S": ["Flughafen Hoexter Holzminden", "Hoexter Holzminden", "Flughafen Hoxter Holzminden", "Hoxter Holzminden"], "woe:hierarchy": {"continent": 24865675, "country": 23424829, "town": 0, "planet": 1, "county": 12596929, "suburb": 0, "state": 2345487, "region": 0, "localadmin": 12624525}, "woe:timezone_id": 28350890, "woe:hash": "u1nwtx0pbgf9", "woe:centroid": [9.38236, 51.807381], "geom:latitude": 51.807381, "geom:longitude": 9.38236, "geom:hash": "u1nwtx0pbgf9", "woe:latitude": 51.807381, "geom:centroid": [9.38236, 51.807381], "woe:longitude": 9.38236, "woe:repo": "woeplanet-airport-de", "geom:area": 0.0, "woe:scale": 19}}