{"type": "Feature", "id": 12513076, "properties": {"woe:id": 12513076, "woe:parent_id": 643787, "woe:name": "Darmstadt Army Air Field", "woe:placetype": 14, "woe:placetype_name": "Airport", "woe:lang": "ENG", "iso:country": "DE", "meta:provider": ["geoplanet:7.3.1", "geoplanet:7.3.2", "geoplanet:7.4.0", "geoplanet:7.4.1", "geoplanet:7.5.1", "geoplanet:7.5.2", "geoplanet:7.6.0", "geoplanet:7.8.1", "geoplanet:7.9.0", "geoplanet:7.10.0", "geoplanet:8.0.0", "woeplanet:8.0.0"], "meta:indexed": "2020-08-20T20:50:56.425322", "meta:updated": "2020-08-22T01:51:21.731661", "woe:hierarchy": {"continent": 24865675, "country": 23424829, "town": 0, "planet": 1, "county": 12597057, "suburb": 0, "state": 2345485, "region": 0, "localadmin": 26822103}, "woe:timezone_id": 28350890, "woe:hash": "u0y5e7y4rvs5", "woe:centroid": [8.5889, 49.855], "geom:latitude": 49.855, "geom:longitude": 8.5889, "geom:hash": "u0y5e7y4rvs5", "woe:latitude": 49.855, "geom:centroid": [8.5889, 49.855], "woe:longitude": 8.5889, "woe:repo": "woeplanet-airport-de"}, "geometry": {"coordinates": [8.5889, 49.855], "type": "Point"}}