{"type": "Feature", "id": 56052156, "geometry": {"type": "Point", "coordinates": [8.96938, 48.93578]}, "properties": {"woe:id": 56052156, "woe:parent_id": 702009, "woe:name": "Segelfluggel\u00e4nde Vaihingen (enz)", "woe:placetype": 14, "woe:placetype_name": "Airport", "woe:lang": "GER", "iso:country": "DE", "meta:provider": ["geoplanet:7.3.1", "geoplanet:7.3.2", "geoplanet:7.4.0", "geoplanet:7.4.1", "geoplanet:7.5.1", "geoplanet:7.5.2", "geoplanet:7.6.0", "geoplanet:7.8.1", "geoplanet:7.9.0", "geoplanet:7.10.0", "geoplanet:8.0.0", "woeplanet:8.0.0"], "meta:indexed": "2020-08-20T20:50:56.836224", "meta:updated": "2020-10-14T11:05:29.371755", "woe:alias_GER_V": ["Segelfluggelande Vaihingen"], "woe:alias_GER_S": ["Segelfluggelande Vaihingen (enz)"], "woe:hierarchy": {"continent": 24865675, "country": 23424829, "town": 0, "planet": 1, "county": 12596746, "suburb": 0, "state": 2345481, "region": 0, "localadmin": 12623241}, "woe:timezone_id": 28350890, "woe:hash": "u0wqkh7r9dw6", "woe:centroid": [8.96938, 48.93578], "geom:latitude": 48.93578, "geom:longitude": 8.96938, "geom:hash": "u0wqkh7r9dw6", "woe:latitude": 48.93578, "geom:centroid": [8.96938, 48.93578], "woe:longitude": 8.96938, "woe:repo": "woeplanet-airport-de", "geom:area": 0.0, "woe:scale": 19}}