{"type": "Feature", "id": 12513171, "properties": {"woe:id": 12513171, "woe:parent_id": 20165709, "woe:name": "Ludwigslust East Airport", "woe:placetype": 14, "woe:placetype_name": "Airport", "woe:lang": "ENG", "iso:country": "DE", "meta:provider": ["geoplanet:7.3.1", "geoplanet:7.3.2", "geoplanet:7.4.0", "geoplanet:7.4.1", "geoplanet:7.5.1", "geoplanet:7.5.2", "geoplanet:7.6.0", "geoplanet:7.8.1", "geoplanet:7.9.0", "geoplanet:7.10.0", "geoplanet:8.0.0", "woeplanet:8.0.0"], "meta:indexed": "2020-08-20T20:50:56.482449", "woe:alias_GER_Q": ["Flughafen Ludwigslust East"], "meta:updated": "2020-08-22T01:51:21.753467", "woe:hierarchy": {"continent": 24865675, "country": 23424829, "town": 0, "planet": 1, "county": 12596989, "suburb": 0, "state": 2345492, "region": 0, "localadmin": 12630733}, "woe:timezone_id": 28350890, "woe:hash": "u32pq812zcs8", "woe:centroid": [11.5377, 53.305801], "geom:latitude": 53.305801, "geom:longitude": 11.5377, "geom:hash": "u32pq812zcs8", "woe:latitude": 53.305801, "geom:centroid": [11.5377, 53.305801], "woe:longitude": 11.5377, "woe:repo": "woeplanet-airport-de"}, "geometry": {"coordinates": [11.5377, 53.305801], "type": "Point"}}