{"type": "Feature", "id": 12513136, "geometry": {"type": "Point", "coordinates": [7.89, 53.534199]}, "properties": {"woe:id": 12513136, "woe:parent_id": 20174729, "woe:name": "Jever Airport", "woe:placetype": 14, "woe:placetype_name": "Airport", "woe:lang": "ENG", "iso:country": "DE", "meta:provider": ["geoplanet:7.3.1", "geoplanet:7.3.2", "geoplanet:7.4.0", "geoplanet:7.4.1", "geoplanet:7.5.1", "geoplanet:7.5.2", "geoplanet:7.6.0", "geoplanet:7.8.1", "geoplanet:7.9.0", "geoplanet:7.10.0", "geoplanet:8.0.0", "woeplanet:8.0.0"], "meta:indexed": "2020-08-20T20:50:56.465808", "woe:alias_GER_Q": ["Flughafen Jever"], "meta:updated": "2020-10-14T11:05:29.502858", "woe:hierarchy": {"continent": 24865675, "country": 23424829, "town": 0, "planet": 1, "county": 12596720, "suburb": 0, "state": 2345486, "region": 0, "localadmin": 12629935}, "woe:timezone_id": 28350890, "woe:hash": "u1t8e9976642", "woe:centroid": [7.89, 53.534199], "geom:latitude": 53.534199, "geom:longitude": 7.89, "geom:hash": "u1t8e9976642", "woe:latitude": 53.534199, "geom:centroid": [7.89, 53.534199], "woe:longitude": 7.89, "woe:repo": "woeplanet-airport-de", "geom:area": 0.0, "woe:scale": 19}}