{"type": "Feature", "id": 56052182, "geometry": {"type": "Point", "coordinates": [9.44543, 48.918941]}, "properties": {"woe:id": 56052182, "woe:parent_id": 636380, "woe:name": "Landeplatz Backnang-heiningen", "woe:placetype": 14, "woe:placetype_name": "Airport", "woe:lang": "GER", "iso:country": "DE", "meta:provider": ["geoplanet:7.3.1", "geoplanet:7.3.2", "geoplanet:7.4.0", "geoplanet:7.4.1", "geoplanet:7.5.1", "geoplanet:7.5.2", "geoplanet:7.6.0", "geoplanet:7.8.1", "geoplanet:7.9.0", "geoplanet:7.10.0", "geoplanet:8.0.0", "woeplanet:8.0.0"], "meta:indexed": "2020-08-20T20:50:56.858411", "meta:updated": "2020-10-14T11:05:29.380696", "woe:hierarchy": {"continent": 24865675, "country": 23424829, "town": 0, "planet": 1, "county": 12596822, "suburb": 0, "state": 2345481, "region": 0, "localadmin": 12624100}, "woe:timezone_id": 28350890, "woe:hash": "u0wwqcmvqrx1", "woe:centroid": [9.44543, 48.918941], "geom:latitude": 48.918941, "geom:longitude": 9.44543, "geom:hash": "u0wwqcmvqrx1", "woe:latitude": 48.918941, "geom:centroid": [9.44543, 48.918941], "woe:longitude": 9.44543, "woe:repo": "woeplanet-airport-de", "geom:area": 0.0, "woe:scale": 19}}