{"type": "Feature", "id": 56052176, "geometry": {"type": "Point", "coordinates": [10.00454, 48.746269]}, "properties": {"woe:id": 56052176, "woe:parent_id": 637075, "woe:name": "Segelfluggel\u00e4nde Bartholom\u00e4", "woe:placetype": 14, "woe:placetype_name": "Airport", "woe:lang": "GER", "iso:country": "DE", "meta:provider": ["geoplanet:7.3.1", "geoplanet:7.3.2", "geoplanet:7.4.0", "geoplanet:7.4.1", "geoplanet:7.5.1", "geoplanet:7.5.2", "geoplanet:7.6.0", "geoplanet:7.8.1", "geoplanet:7.9.0", "geoplanet:7.10.0", "geoplanet:8.0.0", "woeplanet:8.0.0"], "meta:indexed": "2020-08-20T20:50:56.853257", "meta:updated": "2020-10-14T11:05:29.372750", "woe:alias_GER_S": ["Segelfluggelande Bartholoma"], "woe:hierarchy": {"continent": 24865675, "country": 23424829, "town": 0, "planet": 1, "county": 12596698, "suburb": 0, "state": 2345481, "region": 0, "localadmin": 12624204}, "woe:timezone_id": 28350890, "woe:hash": "u0xj79vpdejt", "woe:centroid": [10.00454, 48.746269], "geom:latitude": 48.746269, "geom:longitude": 10.00454, "geom:hash": "u0xj79vpdejt", "woe:latitude": 48.746269, "geom:centroid": [10.00454, 48.746269], "woe:longitude": 10.00454, "woe:repo": "woeplanet-airport-de", "geom:area": 0.0, "woe:scale": 19}}