{"type": "Feature", "id": 56052021, "geometry": {"type": "Point", "coordinates": [8.97366, 49.677059]}, "properties": {"woe:id": 56052021, "woe:parent_id": 675190, "woe:name": "Flugplatz Michelstadt/odenwald", "woe:placetype": 14, "woe:placetype_name": "Airport", "woe:lang": "GER", "iso:country": "DE", "meta:provider": ["geoplanet:7.3.1", "geoplanet:7.3.2", "geoplanet:7.4.0", "geoplanet:7.4.1", "geoplanet:7.5.1", "geoplanet:7.5.2", "geoplanet:7.6.0", "geoplanet:7.8.1", "geoplanet:7.9.0", "geoplanet:7.10.0", "geoplanet:8.0.0", "woeplanet:8.0.0"], "meta:indexed": "2020-08-20T20:50:56.717037", "meta:updated": "2020-10-14T11:05:29.259972", "woe:hierarchy": {"continent": 24865675, "country": 23424829, "town": 0, "planet": 1, "county": 12596865, "suburb": 0, "state": 2345485, "region": 0, "localadmin": 12632551}, "woe:timezone_id": 28350890, "woe:hash": "u0y6s5qmv6vz", "woe:centroid": [8.97366, 49.677059], "geom:latitude": 49.677059, "geom:longitude": 8.97366, "geom:hash": "u0y6s5qmv6vz", "woe:latitude": 49.677059, "geom:centroid": [8.97366, 49.677059], "woe:longitude": 8.97366, "woe:repo": "woeplanet-airport-de", "geom:area": 0.0, "woe:scale": 19}}