{"type": "Feature", "id": 12513105, "geometry": {"type": "Point", "coordinates": [11.2695, 50.7323]}, "properties": {"woe:id": 12513105, "woe:parent_id": 671555, "woe:name": "Gboschwitz Airport", "woe:placetype": 14, "woe:placetype_name": "Airport", "woe:lang": "ENG", "iso:country": "DE", "meta:provider": ["geoplanet:7.3.1", "geoplanet:7.3.2", "geoplanet:7.4.0", "geoplanet:7.4.1", "geoplanet:7.5.1", "geoplanet:7.5.2", "geoplanet:7.6.0", "geoplanet:7.8.1", "geoplanet:7.9.0", "geoplanet:7.10.0", "geoplanet:8.0.0", "woeplanet:8.0.0"], "meta:indexed": "2020-08-20T20:50:56.444029", "woe:alias_GER_Q": ["Flughafen Gboschwitz"], "meta:updated": "2020-10-14T11:05:29.531025", "woe:hierarchy": {"continent": 24865675, "country": 23424829, "town": 0, "planet": 1, "county": 12596965, "suburb": 0, "state": 2345495, "region": 0, "localadmin": 12636406}, "woe:timezone_id": 28350890, "woe:hash": "u30087w1n6hm", "woe:centroid": [11.2695, 50.7323], "geom:latitude": 50.7323, "geom:longitude": 11.2695, "geom:hash": "u30087w1n6hm", "woe:latitude": 50.7323, "geom:centroid": [11.2695, 50.7323], "woe:longitude": 11.2695, "woe:repo": "woeplanet-airport-de", "geom:area": 0.0, "woe:scale": 19}}