{"type": "Feature", "id": 56052023, "geometry": {"type": "Point", "coordinates": [8.71489, 50.36182]}, "properties": {"woe:id": 56052023, "woe:parent_id": 681777, "woe:name": "Flugplatz Ober-m\u00f6rlen", "woe:placetype": 14, "woe:placetype_name": "Airport", "woe:lang": "GER", "iso:country": "DE", "meta:provider": ["geoplanet:7.3.1", "geoplanet:7.3.2", "geoplanet:7.4.0", "geoplanet:7.4.1", "geoplanet:7.5.1", "geoplanet:7.5.2", "geoplanet:7.6.0", "geoplanet:7.8.1", "geoplanet:7.9.0", "geoplanet:7.10.0", "geoplanet:8.0.0", "woeplanet:8.0.0"], "meta:indexed": "2020-08-20T20:50:56.718800", "meta:updated": "2020-10-14T11:05:29.268054", "woe:alias_GER_S": ["Flugplatz Ober-morlen"], "woe:hierarchy": {"continent": 24865675, "country": 23424829, "town": 0, "planet": 1, "county": 12596966, "suburb": 0, "state": 2345485, "region": 0, "localadmin": 12632590}, "woe:timezone_id": 28350890, "woe:hash": "u0ynw21fzesy", "woe:centroid": [8.71489, 50.36182], "geom:latitude": 50.36182, "geom:longitude": 8.71489, "geom:hash": "u0ynw21fzesy", "woe:latitude": 50.36182, "geom:centroid": [8.71489, 50.36182], "woe:longitude": 8.71489, "woe:repo": "woeplanet-airport-de", "geom:area": 0.0, "woe:scale": 19}}