{"type": "Feature", "id": 56052046, "properties": {"woe:id": 56052046, "woe:parent_id": 20162796, "woe:name": "Landeplatz Bad Sobernheim-domberg", "woe:placetype": 14, "woe:placetype_name": "Airport", "woe:lang": "GER", "iso:country": "DE", "meta:provider": ["geoplanet:7.3.1", "geoplanet:7.3.2", "geoplanet:7.4.0", "geoplanet:7.4.1", "geoplanet:7.5.1", "geoplanet:7.5.2", "geoplanet:7.6.0", "geoplanet:7.8.1", "geoplanet:7.9.0", "geoplanet:7.10.0", "geoplanet:8.0.0", "woeplanet:8.0.0"], "meta:indexed": "2020-08-20T20:50:56.738879", "meta:updated": "2020-08-22T01:51:21.872177", "woe:hierarchy": {"continent": 24865675, "country": 23424829, "town": 0, "planet": 1, "county": 12596762, "suburb": 0, "state": 2345488, "region": 0, "localadmin": 12628083}, "woe:timezone_id": 28350890, "woe:hash": "u0v7nrg1bumq", "woe:centroid": [7.66163, 49.78899], "geom:latitude": 49.78899, "geom:longitude": 7.66163, "geom:hash": "u0v7nrg1bumq", "woe:latitude": 49.78899, "geom:centroid": [7.66163, 49.78899], "woe:longitude": 7.66163, "woe:repo": "woeplanet-airport-de"}, "geometry": {"coordinates": [7.66163, 49.78899], "type": "Point"}}