{"type": "Feature", "id": 22193194, "properties": {"woe:id": 22193194, "woe:parent_id": 648351, "woe:name": "Erfurt Airport", "woe:placetype": 14, "woe:placetype_name": "Airport", "woe:lang": "ENG", "iso:country": "DE", "meta:provider": ["geoplanet:7.3.1", "geoplanet:7.3.2", "geoplanet:7.4.0", "geoplanet:7.4.1", "geoplanet:7.5.1", "geoplanet:7.5.2", "geoplanet:7.6.0", "geoplanet:7.8.1", "geoplanet:7.9.0", "geoplanet:7.10.0", "geoplanet:8.0.0", "woeplanet:8.0.0"], "meta:indexed": "2020-08-20T20:50:56.558564", "woe:alias_FIN_V": ["Erfurtin Lentokentt\u00e4", "Erfurtin Lentokentta"], "woe:alias_ENG_V": ["Erfurt-Bindersleben Airport", "ERF", "ERF Airport", "Erfurt Bindersleben"], "woe:alias_ITA_V": ["Aeroporto Di Erfurt-Bindersleben"], "woe:alias_DAN_V": ["Erfurt-Bindersleben Lufthavn"], "woe:alias_DUT_V": ["Luchthaven Erfurt-Bindersleben"], "woe:alias_POR_V": ["Aeropuerto de Erfurt-Bindersleben"], "woe:alias_SWE_V": ["Erfurt-Bindersleben Flygplats"], "woe:alias_GER_Q": ["Flughafen Erfurt"], "meta:updated": "2020-08-22T01:51:21.781936", "woe:alias_GER_V": ["Flughafen Erfurt-Bindersleben", "Flughafen Erfurt Bindersleben", "ERF Flughafen"], "woe:alias_FRE_V": ["Aeroport d'Erfurt-Bindersleben", "A\u00e9roport d'Erfurt-Bindersleben"], "woe:alias_FIN_S": ["Erfurtin Lentokentta"], "woe:alias_FRE_Q": ["A\u00e9roport d'Erfurt-Bindersleben"], "woe:alias_FIN_Q": ["Erfurtin Lentokentt\u00e4"], "woe:alias_HUN_V": ["Erfurt-Bindersleben Repuloter", "Erfurt-Bindersleben Rep\u00fcl\u0151t\u00e9r"], "woe:alias_DUT_Q": ["Luchthaven Erfurt-Bindersleben"], "woe:alias_FRE_S": ["Aeroport d'Erfurt-Bindersleben"], "woe:alias_POL_V": ["Port Lotniczy Erfurt-Bindersleben"], "woe:alias_POR_Q": ["Aeropuerto de Erfurt-Bindersleben"], "woe:alias_DAN_Q": ["Erfurt-Bindersleben Lufthavn"], "woe:alias_CZE_V": ["Letiste Erfurt-Bindersleben", "Leti\u0161t\u011b Erfurt-Bindersleben"], "woe:alias_UNK_V": ["Letisko Erfurt-Bindersleben", "\u0391\u03b5\u03c1\u03bf\u03b4\u03c1\u03bfmu\u03b9\u03bf \u0395\u03c1\u03c6\u03bf\u03c5\u03c1\u03c4\u03b7-\u039c\u03c0\u03b9\u03bd\u03c1\u03c4\u03b5\u03c1\u03c3\u03bb\u03b5mu\u03c0\u03b5\u03bd", "\u0391\u03b5\u03c1\u03bf\u03b4\u03c1\u03bf\u03bc\u03b9\u03bf \u0395\u03c1\u03c6\u03bf\u03c5\u03c1\u03c4\u03b7-\u039c\u03c0\u03b9\u03bd\u03c1\u03c4\u03b5\u03c1\u03c3\u03bb\u03b5\u03bc\u03c0\u03b5\u03bd", "\u0410\u044d\u0440\u043e\u043f\u043e\u0440\u0442 \u042d\u0440\u0444\u0443\u0440\u0442-\u0411\u0438\u043d\u0434\u0435\u0440\u0441\u043b\u0435\u0431\u0435\u043d"], "woe:alias_SWE_Q": ["Erfurt-Bindersleben Flygplats"], "woe:alias_ITA_Q": ["Aeroporto Di Erfurt-Bindersleben"], "woe:hierarchy": {"continent": 24865675, "country": 23424829, "town": 0, "planet": 1, "county": 12596925, "suburb": 0, "state": 2345495, "region": 0, "localadmin": 26822297}, "woe:timezone_id": 28350890, "woe:hash": "u1pccrwq14gd", "woe:centroid": [10.962, 50.974861], "geom:latitude": 50.974861, "geom:longitude": 10.962, "geom:hash": "u1pccrwq14gd", "woe:latitude": 50.974861, "geom:centroid": [10.962, 50.974861], "woe:longitude": 10.962, "woe:repo": "woeplanet-airport-de"}, "geometry": {"coordinates": [10.962, 50.974861], "type": "Point"}}