{"type": "Feature", "id": 56052212, "geometry": {"type": "Point", "coordinates": [9.65149, 48.62241]}, "properties": {"woe:id": 56052212, "woe:parent_id": 655402, "woe:name": "Segelfluggel\u00e4nde", "woe:placetype": 14, "woe:placetype_name": "Airport", "woe:lang": "GER", "iso:country": "DE", "meta:provider": ["geoplanet:7.3.1", "geoplanet:7.3.2", "geoplanet:7.4.0", "geoplanet:7.4.1", "geoplanet:7.5.1", "geoplanet:7.5.2", "geoplanet:7.6.0", "geoplanet:7.8.1", "geoplanet:7.9.0", "geoplanet:7.10.0", "geoplanet:8.0.0", "woeplanet:8.0.0"], "meta:indexed": "2020-08-20T20:50:56.884925", "meta:updated": "2020-10-14T11:05:29.228652", "woe:alias_GER_S": ["Segelfluggelande"], "woe:hierarchy": {"continent": 24865675, "country": 23424829, "town": 0, "planet": 1, "county": 12596800, "suburb": 0, "state": 2345481, "region": 0, "localadmin": 12624078}, "woe:timezone_id": 28350890, "woe:hash": "u0wueekn040t", "woe:centroid": [9.65149, 48.62241], "geom:latitude": 48.62241, "geom:longitude": 9.65149, "geom:hash": "u0wueekn040t", "woe:latitude": 48.62241, "geom:centroid": [9.65149, 48.62241], "woe:longitude": 9.65149, "woe:repo": "woeplanet-airport-de", "geom:area": 0.0, "woe:scale": 19}}