{"type": "Feature", "id": 56052219, "geometry": {"type": "Point", "coordinates": [10.2161, 48.636971]}, "properties": {"woe:id": 56052219, "woe:parent_id": 652499, "woe:name": "Landeplatz Giengen An Der Brenz", "woe:placetype": 14, "woe:placetype_name": "Airport", "woe:lang": "GER", "iso:country": "DE", "meta:provider": ["geoplanet:7.3.1", "geoplanet:7.3.2", "geoplanet:7.4.0", "geoplanet:7.4.1", "geoplanet:7.5.1", "geoplanet:7.5.2", "geoplanet:7.6.0", "geoplanet:7.8.1", "geoplanet:7.9.0", "geoplanet:7.10.0", "geoplanet:8.0.0", "woeplanet:8.0.0"], "meta:indexed": "2020-08-20T20:50:56.891356", "meta:updated": "2020-10-14T11:05:29.219437", "woe:hierarchy": {"continent": 24865675, "country": 23424829, "town": 0, "planet": 1, "county": 12597050, "suburb": 0, "state": 2345481, "region": 0, "localadmin": 12624196}, "woe:timezone_id": 28350890, "woe:hash": "u0xk8qp4uks3", "woe:centroid": [10.2161, 48.636971], "geom:latitude": 48.636971, "geom:longitude": 10.2161, "geom:hash": "u0xk8qp4uks3", "woe:latitude": 48.636971, "geom:centroid": [10.2161, 48.636971], "woe:longitude": 10.2161, "woe:repo": "woeplanet-airport-de", "geom:area": 0.0, "woe:scale": 19}}