{"type": "Feature", "id": 12513165, "properties": {"woe:id": 12513165, "woe:parent_id": 641865, "woe:name": "Leipheim Airport", "woe:placetype": 14, "woe:placetype_name": "Airport", "woe:lang": "ENG", "iso:country": "DE", "meta:provider": ["geoplanet:7.3.1", "geoplanet:7.3.2", "geoplanet:7.4.0", "geoplanet:7.4.1", "geoplanet:7.5.1", "geoplanet:7.5.2", "geoplanet:7.6.0", "geoplanet:7.8.1", "geoplanet:7.9.0", "geoplanet:7.10.0", "geoplanet:8.0.0", "woeplanet:8.0.0"], "meta:indexed": "2020-08-20T20:50:56.480219", "woe:alias_GER_Q": ["Flughafen Leipheim"], "meta:updated": "2020-08-22T01:51:21.752652", "woe:hierarchy": {"continent": 24865675, "country": 23424829, "town": 0, "planet": 1, "county": 12596910, "suburb": 0, "state": 2345482, "region": 0, "localadmin": 12634824}, "woe:timezone_id": 28350890, "woe:hash": "u0x78fqhh7sg", "woe:centroid": [10.2367, 48.4408], "geom:latitude": 48.4408, "geom:longitude": 10.2367, "geom:hash": "u0x78fqhh7sg", "woe:latitude": 48.4408, "geom:centroid": [10.2367, 48.4408], "woe:longitude": 10.2367, "woe:repo": "woeplanet-airport-de"}, "geometry": {"coordinates": [10.2367, 48.4408], "type": "Point"}}