{"type": "Feature", "id": 56052117, "geometry": {"type": "Point", "coordinates": [11.14721, 53.01572]}, "properties": {"woe:id": 56052117, "woe:parent_id": 672860, "woe:name": "Flugplatz L\u00fcchow-rehbeck", "woe:placetype": 14, "woe:placetype_name": "Airport", "woe:lang": "GER", "iso:country": "DE", "meta:provider": ["geoplanet:7.3.1", "geoplanet:7.3.2", "geoplanet:7.4.0", "geoplanet:7.4.1", "geoplanet:7.5.1", "geoplanet:7.5.2", "geoplanet:7.6.0", "geoplanet:7.8.1", "geoplanet:7.9.0", "geoplanet:7.10.0", "geoplanet:8.0.0", "woeplanet:8.0.0"], "meta:indexed": "2020-08-20T20:50:56.800764", "meta:updated": "2020-10-14T11:05:29.331697", "woe:alias_GER_S": ["Flugplatz Luchow-rehbeck"], "woe:hierarchy": {"continent": 24865675, "country": 23424829, "town": 0, "planet": 1, "county": 12596992, "suburb": 0, "state": 2345486, "region": 0, "localadmin": 12629656}, "woe:timezone_id": 28350890, "woe:hash": "u1rvtejnuyd0", "woe:centroid": [11.14721, 53.01572], "geom:latitude": 53.01572, "geom:longitude": 11.14721, "geom:hash": "u1rvtejnuyd0", "woe:latitude": 53.01572, "geom:centroid": [11.14721, 53.01572], "woe:longitude": 11.14721, "woe:repo": "woeplanet-airport-de", "geom:area": 0.0, "woe:scale": 19}}